{"version":1,"resource":"file:///home/mailerdaemon/Projects/buvesz/app/index.tsx","entries":[{"id":"4qbh.tsx","timestamp":1762501835764},{"id":"zHgQ.tsx","timestamp":1762501892279},{"id":"FTUJ.tsx","source":"undoRedo.source","timestamp":1762501931614},{"id":"BpiM.tsx","timestamp":1762502002662},{"id":"8pYZ.tsx","source":"undoRedo.source","timestamp":1762502012012},{"id":"Ltvn.tsx","timestamp":1762502018276},{"id":"TKwA.tsx","timestamp":1762502061892},{"id":"mpJM.tsx","timestamp":1762502142284},{"id":"P6br.tsx","timestamp":1762502195186},{"id":"f4MU.tsx","timestamp":1762502209899},{"id":"jbrw.tsx","timestamp":1762502247945},{"id":"PIKs.tsx","timestamp":1762502299279},{"id":"Afdb.tsx","timestamp":1762502349708},{"id":"pyQ1.tsx","timestamp":1762502391161},{"id":"oRKH.tsx","timestamp":1762502410275},{"id":"08WB.tsx","timestamp":1762502483700},{"id":"rhRd.tsx","timestamp":1762502590905},{"id":"YuuO.tsx","timestamp":1762502645979},{"id":"HEE4.tsx","timestamp":1762502720620},{"id":"kQ4A.tsx","timestamp":1762502759066},{"id":"neoz.tsx","timestamp":1762502785145},{"id":"eCvE.tsx","timestamp":1762502806181},{"id":"6MOj.tsx","timestamp":1762502824744},{"id":"etDq.tsx","source":"undoRedo.source","timestamp":1762502829591},{"id":"qXuO.tsx","timestamp":1762502848180},{"id":"atm5.tsx","timestamp":1762502897800},{"id":"2jFR.tsx","timestamp":1762502978160},{"id":"f08X.tsx","timestamp":1762503060887},{"id":"UsId.tsx","timestamp":1762503131410},{"id":"rtlw.tsx","timestamp":1762503155637},{"id":"CR78.tsx","timestamp":1762503193115},{"id":"d8Ry.tsx","timestamp":1762503273897},{"id":"Sv4E.tsx","timestamp":1762503401728},{"id":"qRcT.tsx","source":"undoRedo.source","timestamp":1762503403389},{"id":"d6QT.tsx","timestamp":1762503415774},{"id":"1xRj.tsx","timestamp":1762503431995},{"id":"R0dY.tsx","timestamp":1762503471823},{"id":"ROJJ.tsx","timestamp":1762503491331},{"id":"KbGV.tsx","timestamp":1762503542172},{"id":"KJMo.tsx","timestamp":1762503656603},{"id":"AlEy.tsx","timestamp":1762503671739},{"id":"OwlG.tsx","timestamp":1762503703452},{"id":"lViP.tsx","timestamp":1762503756682},{"id":"QaUk.tsx","timestamp":1762503783907},{"id":"KBwj.tsx","timestamp":1762503813372},{"id":"E1mJ.tsx","timestamp":1762503840325},{"id":"AhSe.tsx","timestamp":1762503864444},{"id":"lqSt.tsx","timestamp":1762504099649},{"id":"0XYa.tsx","timestamp":1762504211220},{"id":"jvgS.tsx","source":"undoRedo.source","timestamp":1762504228354}]}